openportal-0.20.2.dist-info/METADATA
openportal-0.20.2.dist-info/WHEEL
openportal/__init__.py
openportal/openportal.cpython-314-darwin.so
openportal-0.20.2.dist-info/RECORD
