Metadata-Version: 2.4
Name: openportal
Version: 0.20.2
Summary: Python wrappers for OpenPortal
Home-Page: https://github.com/isambard-sc/openportal/
License: MIT
Project-URL: Homepage, https://github.com/isambard-sc/openportal/
Project-URL: Source Code, https://github.com/isambard-sc/openportal/
